pdfworkshop/__init__.py
pdfworkshop/__main__.py
pdfworkshop/_definitions.py
pdfworkshop/cli.py
pdfworkshop/config.ini
pdfworkshop/config.py
pdfworkshop/pdfworkshop.py
pdfworkshop-1.1.2.dist-info/entry_points.txt
pdfworkshop-1.1.2.dist-info/LICENSE
pdfworkshop-1.1.2.dist-info/WHEEL
pdfworkshop-1.1.2.dist-info/METADATA
pdfworkshop-1.1.2.dist-info/RECORD
