Metadata-Version: 2.1
Name: pdfworkshop
Version: 1.1.2
Summary: PDF compressor utility, using iLovePDF API
Home-page: https://github.com/eden-box/pdfworkshop
License: MIT
Keywords: python,pdf,compress,ilovepdf
Author: Eden-Box
Author-email: dev@edenbox.cf
Requires-Python: >=3.6,<4.0
Classifier: Development Status :: 5 - Production/Stable
Classifier: License :: OSI Approved :: MIT License
Classifier: Natural Language :: English
Classifier: Operating System :: OS Independent
Classifier: Programming Language :: Python :: 3
Classifier: Programming Language :: Python :: 3.6
Classifier: Programming Language :: Python :: 3.7
Classifier: Topic :: Office/Business
Classifier: Topic :: Utilities
Requires-Dist: appdirs (>=1.4.3,<1.5.0)
Requires-Dist: binpacking (>=1.4.1,<1.5.0)
Requires-Dist: click (>=7.0,<7.1)
Requires-Dist: edenpdf (>=1.0.3,<2.0.0)
Project-URL: Repository, https://github.com/eden-box/pdfworkshop
